{
  "twitter": [],
  "reddit": [],
  "google_trends": [
    {
      "keyword": "personalized gifts",
      "interest_score": 8,
      "trend": "stable"
    },
    {
      "keyword": "wedding gift ideas",
      "interest_score": 37,
      "trend": "stable"
    }
  ],
  "tiktok": [
    {
      "hashtag": "#giftideas",
      "estimated_views": "High",
      "relevance": "gifts"
    },
    {
      "hashtag": "#personalizedgifts",
      "estimated_views": "High",
      "relevance": "gifts"
    },
    {
      "hashtag": "#uniquegifts",
      "estimated_views": "High",
      "relevance": "gifts"
    },
    {
      "hashtag": "#weddinggifts",
      "estimated_views": "High",
      "relevance": "gifts"
    },
    {
      "hashtag": "#creativegifts",
      "estimated_views": "High",
      "relevance": "gifts"
    },
    {
      "hashtag": "#giftinspo",
      "estimated_views": "High",
      "relevance": "gifts"
    }
  ],
  "competitors": [
    {
      "name": "Moonpig",
      "url": "https://www.moonpig.com",
      "status": "monitored",
      "focus": "personalized gifts"
    },
    {
      "name": "Funky Pigeon",
      "url": "https://www.funkypigeon.com",
      "status": "monitored",
      "focus": "personalized gifts"
    },
    {
      "name": "Not On The High Street",
      "url": "https://www.notonthehighstreet.com",
      "status": "monitored",
      "focus": "personalized gifts"
    },
    {
      "name": "Prezzybox",
      "url": "https://www.prezzybox.com",
      "status": "monitored",
      "focus": "personalized gifts"
    }
  ],
  "analysis": {
    "themes": [
      "10 Unique Personalized Wedding Gift Ideas for UK Couples in 2025",
      "How to Add a Personal Touch to Wedding Favours with SayPlay Voice Stickers",
      "Beyond the Card: Why Voice Message Stickers Are the Ultimate 2025 Gift Trend",
      "The Best Personalised Wedding Keepsakes for UK Brides and Grooms in 2025",
      "5 Creative Ways to Use SayPlay Voice Stickers for Memorable Wedding Gifting"
    ]
  }
}